stempy/__init__.py
stempy/_image.cpython-38-x86_64-linux-gnu.so
stempy/_io.cpython-38-x86_64-linux-gnu.so
stempy/libstem.so
stempy/utils.py
stempy/contrib/__init__.py
stempy/image/__init__.py
stempy/io/__init__.py
stempy/io/compatibility.py
stempy/io/sparse_array.py
stempy/pipeline/__init__.py
stempy-3.4.1.data/data/include/stempy/config.h
stempy-3.4.1.data/data/include/stempy/electron.h
stempy-3.4.1.data/data/include/stempy/image.h
stempy-3.4.1.data/data/include/stempy/mask.h
stempy-3.4.1.data/data/include/stempy/reader.h
stempy-3.4.1.data/data/include/thirdparty/ThreadPool/ThreadPool.h
stempy-3.4.1.data/data/lib64/libstem.so
stempy-3.4.1.data/data/lib64/cmake/stempy/stempyConfig.cmake
stempy-3.4.1.data/data/lib64/cmake/stempy/stempyTargets-release.cmake
stempy-3.4.1.data/data/lib64/cmake/stempy/stempyTargets.cmake
stempy.libs/libaec-91f0ca0f.so.0.0.8
stempy.libs/libhdf5-b5e70f84.so.103.1.0
stempy.libs/libsz-0deeef7d.so.2.0.1
stempy-3.4.1.dist-info/LICENSE
stempy-3.4.1.dist-info/METADATA
stempy-3.4.1.dist-info/WHEEL
stempy-3.4.1.dist-info/top_level.txt
stempy-3.4.1.dist-info/RECORD
